{
    "title": "臺灣嘉義地方法院 112 年度附民字第 206 號刑事裁定",
    "maintext": "本件移送本院民事庭",
    "persons": [
        [
            "法官",
            "吳育汝"
        ],
        [
            "書記官",
            "黃士祐"
        ],
        [
            "被告",
            "林福傳"
        ],
        [
            "法官",
            "林正雄"
        ],
        [
            "原告",
            "林明助"
        ]
    ],
    "location": [],
    "date": [
        "112年6月8日"
    ],
    "bad_words": [],
    "fine": "",
    "days": "",
    "laws": [
        "刑事訴訟法第504條"
    ],
    "result": "本件移送本院民事庭",
    "text": "臺灣嘉義地方法院刑事附帶民事訴訟裁定112年度附民字第206號原告林明助被告林福傳上列被告因本院112年度朴簡字第147號（原案號：112年度易字第273號）公然侮辱案件，經原告提起附帶民事訴訟，請求損害賠償，本院裁定如下：主文本件移送本院民事庭。理由一、查原告林明助對本院112年度朴簡字第147號，被告林福傳公然侮辱案件，提起附帶民事訴訟，請求損害賠償事件，因其內容確係繁雜，非經長久時日，不能終結其審判，爰將本件附帶民事訴訟移送本院民事庭。二、依刑事訴訟法第504條第1項規定，裁定如主文。中華民國112年6月8日刑事第二庭審判長法官林正雄法官官怡臻法官吳育汝上列正本證明與原本無異。本件不得抗告。中華民國112年6月8日書記官黃士祐"
}