{
    "title": "臺灣高等法院 高雄分院刑事105,上易,178",
    "maintext": "上訴駁回",
    "persons": [
        [
            "法官",
            "徐美麗"
        ],
        [
            "檢察官",
            "曾文鐘"
        ],
        [
            "法官",
            "黃蕙芳"
        ],
        [
            "被告",
            "鍾鳳娣"
        ],
        [
            "被告",
            "陳文鵬"
        ],
        [
            "法官",
            "李炫德"
        ],
        [
            "書記官",
            "陳昱光"
        ]
    ],
    "location": [
        "屏東",
        "屏東縣",
        "屏東縣內埔鄉",
        "○○路"
    ],
    "date": [
        "105年1月22日",
        "103年12月6日14時",
        "105年5月19日",
        "103年12月6日"
    ],
    "bad_words": [
        "下三濫的人",
        "真不要臉",
        "真不要臉耶",
        "下三",
        "很不要臉耶"
    ],
    "fine": "",
    "days": "",
    "laws": [
        "刑事訴訟法159-1",
        "刑事訴訟法159-2",
        "刑事訴訟法368",
        "刑事訴訟法159-5",
        "中華民國刑法施行法1-1 1",
        "中華民國刑法57",
        "刑事訴訟法159-4",
        "刑事訴訟法159-3",
        "中華民國刑法309 1",
        "中華民國刑法309",
        "中華民國刑法施行法1-1 2",
        "中華民國刑法42 3"
    ],
    "result": "上訴駁回",
    "text": "臺灣高等法院高雄分院刑事判決105年度上易字第178號上訴人即被告陳文鵬鍾鳳娣上一人送達代收人陳文鵬上列上訴人因公然侮辱案件，不服臺灣屏東地方法院104年度審易字第948號，中華民國105年1月22日第一審判決（起訴案號：臺灣屏東地方法院檢察署104年度偵續字第47號），提起上訴，本院判決如下：主文上訴駁回。事實一、陳文鵬與鍾鳳娣為夫妻關係，2人所共有之屏東縣內埔鄉○○村○○路000巷00號房屋，與曾玫馨所居住之屏東縣內埔鄉○○村○○路000巷0號房屋相互毗鄰，民國103年12月6日前，雙方已因曾玫馨在上開2房屋前空地（起訴書記載為庭院）之入口處設置鐵門而生嫌隙。嗣於103年12月6日14時許，雙方在上開空地內，又因鐵門設置問題發生爭執，曾玫馨即持數位相機與其兄曾先授對陳文鵬、鍾鳳娣2人進行蒐證，陳文鵬、鍾鳳娣見狀因而心生不滿，竟各別基於公然侮辱之犯意，在上開不特定人得以共見或共聞之公共場所，由陳文鵬接續以「真不要臉耶」、「很不要臉耶」之粗鄙言語，另鍾鳳娣以「下三、下三濫的人」之粗鄙言語，公然辱罵曾玫馨，而以此方式公然侮辱曾玫馨（公然侮辱曾先授部分未據告訴）。二、案經曾玫馨訴由屏東縣政府警察局內埔分局報告臺灣屏東地方法院檢察署檢察官偵查起訴。理由壹、程序方面按被告以外之人於審判外之陳述，雖不符前4條之規定，而經當事人於審判程序同意作為證據，法院審酌該言詞陳述或書面陳述作成時之情況，認為適當者，亦得為證據。當事人、代理人或辯護人於法院調查證據時，知有第159條第1項不得為證據之情形，而未於言詞辯論終結前聲明異議者，視為有前項之同意，刑事訴訟法第159條之5定有明文。本件作為證據使用而不符刑事訴訟法第159條之1至第159條之4規定之相關審判外陳述，未經檢察官、上訴人即被告（下稱被告）陳文鵬、鍾鳳娣於本院審理過程中聲明異議，本院並審酌上開陳述作成時之情況正常，所取得過程並無瑕疵，且與本案相關之待證事實具有關連性，認適當作為證據，依前開刑事訴訟法第159條之5之規定，認均具有證據能力。貳、實體方面一、認定犯罪事實所憑之證據及理由上開事實，業據被告陳文鵬、鍾鳳娣2人分別於原審及本院坦承不諱（見原審卷第17頁反面、21頁；本院卷第30頁正反面），核與告訴人曾玫馨於警詢及偵查證述情節相合（見警卷第2頁反面、偵一卷第36-37頁），並有告訴人提出之錄影光碟1片、光碟影片檔內容說明在卷可稽（見警卷第12頁反面、偵二卷卷底證物袋內）。又經檢察事務官勘驗上開錄影光碟，被告陳文鵬、鍾鳳娣曾分別出口辱罵如事實欄所載之「真不要臉」、「很不要臉耶」、「下三、下三濫的人」等言語，有該勘驗筆錄1份及錄影畫面、內容等在卷可稽（見偵一卷第38至41頁），足認被告2人之自白與事實相合，可資採為認定犯罪事實之依據，本案事證明確，被告2人犯行均堪以認定。另被告2人應係分別以前揭粗鄙言語侮辱曾玫馨，有上開勘驗筆錄可參，起訴書所載與前揭侮辱言語稍有不同，應予補充。二、論罪部分查被告2人於不特定人得以共見或共聞之狀況下，分別以事實欄所載言語，謾罵告訴人，足以貶損告訴人之人格評價與社會地位，是核被告2人所為，各係犯刑法第309條第1項之公然侮辱罪。被告陳文鵬先後以「真不要臉耶」、「很不要臉耶」等語辱罵告訴人，因係基於侮辱告訴人之單一目的而同時所為之數個舉動，因其侵害之法益同一，且數行為係在密切接近之時間、地點實施，各行為之獨立性極為薄弱，依一般社會健全觀念，在時間差距上，難以強行分開，在刑法評價上，應視為數個舉動之接續施行，應屬接續犯，而為包括之一罪。三、上訴駁回之理由(一)原審認被告2人罪證明確，因而適用刑法第309條第1項、第42條第3項、刑法施行法第1條之1第1項、第2項前段規定，並審酌被告2人縱不滿告訴人所為，亦應依循正軌處理，自不得施以貶低告訴人人格之手段，詎其等不思此為，貿然為本件公然侮辱之犯行，嗣猶未能與告訴人達成和解或對之有所賠償，所為均有不該，惟考量被告2人均無任何前科紀錄，此有臺灣高等法院被告前案紀錄表2份在卷可按，素行均非不良，且其等於犯後均能坦承犯行，另其等無非係因在前有嫌隙之下，一時失慮所致而為本案犯行，兼衡其等之犯罪手段、學歷（警卷第5、7頁記載2人均為大學畢業，被告鍾鳳娣於本院陳稱係研究所畢業，見本院卷第32頁反面，予以補充，原審誤載為大學畢業，應予更正）、家庭暨其職業狀況（家境屬小康，陳文鵬為農會職員、鍾鳳娣為高中教師）等一切情狀，各別量處罰金新台幣（下同）5,000元，並均諭知如易服勞役以1千元折算1日之標準。經核原判決認事用法，核無不合，量刑亦已斟酌刑法第57條各款所列情狀，而未逾越法定範圍，亦未濫用其職權，應屬適當。(二)被告2人上訴意旨略以：知名作家張大春犯公然侮辱罪，僅判處罰金3,000元，被告等為泛泛之輩、無名小子，同犯公然侮辱罪，卻判罰金5,000元，是否應依當事人之社會名望、對社會影響力大小而作為判決，請求從輕量刑云云。(三)按關於刑之量定，係實體法上賦予法院得為自由裁量之事項，倘其未有逾越法律所規定之範圍，或濫用其權限，即不得任意指摘為違法（最高法院75年度台上字第7033號判例意旨參照）。且在同一犯罪事實與情節，如別無其他加重或減輕之原因，下級審量定之刑，亦無過重或失輕之不當情形，則上級審法院對下級審法院之職權行使，原則上應予尊重（最高法院85年度台上字第2446號判決意旨參照）。查本案原審對被告之量刑，非僅泛稱審酌被告之品行、犯罪之動機、目的、手段、犯後態度等法律抽象之一般規定（最高法院94年度台上字第2131號判決意旨參照），而係就各該事由之具體事實，已詳敘上揭各種量刑條件之具體理由，核原審量刑既未逾法定刑度，又無濫用量刑權限之情形，於國家刑罰權在本案實踐個別正義而言，應屬罪刑相當，刑度亦屬妥適，並無過重之情事，且合乎法律之目的，並無違背內部性界限，亦無權利濫用之違法，或違反比例原則、平等原則、公平正義等法則。又依被告2人上訴意旨所提出關於張大春之資料內容（見本院卷第5頁），與本件之犯罪動機（本件為被告2人與告訴人因設置鐵門一事有所嫌隙；張大春案則為張大春因收聽電台節目對於廣播主持人之言論生氣）、犯罪手段（本件為當場辱罵告訴人並有其他毀損、傷害情事，已據告訴人於警詢陳述在卷；而張大春案則為張大春在臉書留言），二案發生之緣由、經過均有不同，是自難以張大春案判處罰金3,000元，本件則應為較輕之判決。故被告2人徒以上開理由及原審已審酌之內容指摘原審量刑過重，尚難認有理由。從而，原判決判處被告2人罰金各5,000元，所為量刑應屬允當，被告2人上訴，均為無理由，均應予駁回。據上論結，應依刑事訴訟法第368條，判決如主文。本案經檢察官曾文鐘到庭執行職務。中華民國105年5月19日刑事第八庭審判長法官李炫德法官徐美麗法官黃蕙芳以上正本證明與原本無異。不得上訴。中華民國105年5月19日書記官陳昱光附錄本判決論罪科刑法條：刑法第309條公然侮辱人者，處拘役或3百元以下罰金。以強暴犯前項之罪者，處1年以下有期徒刑、拘役或5百元以下罰金。"
}